Metadata-Version: 1.1
Name: textinput
Version: 0.2.0
Summary: streamlined version of stdlib fileinput
Home-page: UNKNOWN
Author: Michael Hoffman
Author-email: michael.hoffman@utoronto.ca
License: GNU GPLv2
Platform: UNKNOWN
Classifier: License :: OSI Approved :: GNU General Public License (GPL)
Classifier: Natural Language :: English
Classifier: Programming Language :: Python
